kraky/__init__.py
kraky/api.py
kraky/cli.py
kraky/log.py
kraky/py.typed
kraky/ws.py
kraky-2023.8.17.dist-info/METADATA
kraky-2023.8.17.dist-info/WHEEL
kraky-2023.8.17.dist-info/entry_points.txt
kraky-2023.8.17.dist-info/licenses/LICENSE
kraky-2023.8.17.dist-info/RECORD
