Metadata-Version: 2.1
Name: kraky
Version: 2023.8.17
Summary: Python client for Kraken API REST and Kraken Websockets API using httpx and websockets. Supports both sync and async for API REST.
Author-email: Atem18 <contact@atemlire.io>
License: MIT License
License-File: LICENSE
Keywords: asyncio,httpx,kraken,websockets
Classifier: License :: OSI Approved :: MIT License
Classifier: Programming Language :: Python :: 3
Classifier: Programming Language :: Python :: 3.8
Classifier: Programming Language :: Python :: 3.9
Classifier: Programming Language :: Python :: 3.10
Classifier: Programming Language :: Python :: 3.11
Requires-Dist: httpx<0.25.0,>=0.23.3
Requires-Dist: python-dotenv<1.1.0,>=0.21.1
Requires-Dist: typer<0.10,>=0.7
Requires-Dist: websockets<12.0,>=10.4
Provides-Extra: build
Requires-Dist: hatch==1.7.0; extra == 'build'
Provides-Extra: dev
Requires-Dist: mypy==1.5.0; extra == 'dev'
Requires-Dist: pre-commit<4.0.0,>=2.17.0; extra == 'dev'
Requires-Dist: ruff==0.0.284; extra == 'dev'
Provides-Extra: doc
Requires-Dist: mkdocs-material==9.1.21; extra == 'doc'
Requires-Dist: mkdocs==1.5.2; extra == 'doc'
Requires-Dist: mkdocstrings-python==1.3.0; extra == 'doc'
Requires-Dist: mkdocstrings==0.22.0; extra == 'doc'
Provides-Extra: test
Requires-Dist: pytest-asyncio==0.21.1; extra == 'test'
Requires-Dist: pytest==7.4.0; extra == 'test'
Requires-Dist: tox==4.7.0; extra == 'test'
